beerme/__init__.py
beerme/beerme.py
beerme-1.1.dist-info/METADATA
beerme-1.1.dist-info/WHEEL
beerme-1.1.dist-info/entry_points.txt
beerme-1.1.dist-info/top_level.txt
beerme-1.1.dist-info/RECORD
