Metadata-Version: 2.1
Name: beerme
Version: 1.1
Summary: Untapped beer list scraper for Big Hops San Antonio
Home-page: https://github.com/jr0d/beerme
Author: Jared Rodriguez
Author-email: jared@blacknode.net
License: UNKNOWN
Keywords: BigHops,beer
Platform: UNKNOWN
Requires-Dist: beautifulsoup4
Requires-Dist: requests
